openclean_notebook/__init__.py
openclean_notebook/engine.py
openclean_notebook/version.py
openclean_notebook/controller/__init__.py
openclean_notebook/controller/comm.py
openclean_notebook/controller/html.py
openclean_notebook/controller/spreadsheet/__init__.py
openclean_notebook/controller/spreadsheet/base.py
openclean_notebook/controller/spreadsheet/data.py
openclean_notebook/controller/spreadsheet/schema.json
openclean_notebook/metadata/datamart.py
openclean_notebook/ui/build/opencleanVis.js
openclean_notebook/ui/templates/spreadsheet.html
openclean_notebook-0.1.7.dist-info/LICENSE
openclean_notebook-0.1.7.dist-info/METADATA
openclean_notebook-0.1.7.dist-info/WHEEL
openclean_notebook-0.1.7.dist-info/top_level.txt
openclean_notebook-0.1.7.dist-info/RECORD
