Metadata-Version: 2.1
Name: openclean-notebook
Version: 0.1.7
Summary: openclean Notebook UI Package
Home-page: https://github.com/VIDA-NYU/openclean_notebook
Author: New York University
Author-email: heiko.muller@gmail.com
License: UNKNOWN
Keywords: data cleaning,data profiling,user interface
Platform: UNKNOWN
Classifier: License :: OSI Approved :: BSD License
Classifier: Operating System :: OS Independent
Classifier: Programming Language :: Python :: 3
Classifier: Programming Language :: Python :: 3.7
Classifier: Programming Language :: Python :: 3.8
Classifier: Programming Language :: Python :: 3.9
Classifier: Programming Language :: Python
Requires-Dist: future
Requires-Dist: jsonschema (==3.2.0)
Requires-Dist: openclean-core (>=0.4.0)
Requires-Dist: datamart-profiler (==0.9)
Provides-Extra: dev
Requires-Dist: flake8 ; extra == 'dev'
Requires-Dist: python-language-server ; extra == 'dev'
Requires-Dist: coverage (>=4.0) ; extra == 'dev'
Requires-Dist: pytest ; extra == 'dev'
Requires-Dist: pytest-cov ; extra == 'dev'
Requires-Dist: tox ; extra == 'dev'
Provides-Extra: docs
Requires-Dist: Sphinx ; extra == 'docs'
Requires-Dist: sphinx-rtd-theme ; extra == 'docs'
Provides-Extra: jupyter
Requires-Dist: jupyter ; extra == 'jupyter'
Provides-Extra: tests
Requires-Dist: coverage (>=4.0) ; extra == 'tests'
Requires-Dist: pytest ; extra == 'tests'
Requires-Dist: pytest-cov ; extra == 'tests'
Requires-Dist: tox ; extra == 'tests'
